secure_bite/__init__.py
secure_bite/apps.py
secure_bite/auth_registry.py
secure_bite/authentication.py
secure_bite/defaults.py
secure_bite/middleware.py
secure_bite/models.py
secure_bite/provider_registry.py
secure_bite/serializers.py
secure_bite/signals.py
secure_bite/urls.py
secure_bite/utils.py
secure_bite/views.py
secure_bite/auth_providers/oauth2.py
secure_bite/migrations/0001_initial.py
secure_bite/migrations/__init__.py
secure_bite-0.1.4.dist-info/licenses/LICENSE
secure_bite-0.1.4.dist-info/METADATA
secure_bite-0.1.4.dist-info/WHEEL
secure_bite-0.1.4.dist-info/top_level.txt
secure_bite-0.1.4.dist-info/RECORD
