Metadata-Version: 2.4
Name: secure_bite
Version: 0.1.4
Summary: A secure authentication and session management system for Django
Home-page: https://github.com/Mbulelo-Peyi/secure_bite
Author: Mbulelo Peyi
Author-email: Mbulelo Peyi <notseenyet013@gmail.com>
License: Apache License
Project-URL: Homepage, https://github.com/Mbulelo-Peyi/secure_bite
Project-URL: Repository, https://github.com/Mbulelo-Peyi/secure_bite
Requires-Python: >=3.8
License-File: LICENSE
Requires-Dist: Django>=3.2
Requires-Dist: djangorestframework
Requires-Dist: djangorestframework-simplejwt
Requires-Dist: django-cors-headers
Requires-Dist: django-allauth>=0.60.0
Requires-Dist: dj-rest-auth>=6.0.0
Dynamic: author
Dynamic: home-page
Dynamic: license-file
Dynamic: requires-python
